wivw_demo/__init__.py
wivw_demo/mytool.py
wivw_demo-0.0.9.dist-info/METADATA
wivw_demo-0.0.9.dist-info/WHEEL
wivw_demo-0.0.9.dist-info/top_level.txt
wivw_demo-0.0.9.dist-info/RECORD
