Metadata-Version: 2.1
Name: wivw-demo
Version: 0.0.9
Summary: 我的工具
Home-page: https://github.com/wivw0306/wivw-demo-py
Author: freeflyday
Author-email: freeflyday@163.com
License: MIT License
Project-URL: Documentation, https://redis.readthedocs.io/en/latest/
Project-URL: Changes, https://github.com/redis/redis-py/releases
Project-URL: Code, https://github.com/redis/redis-py
Project-URL: Issue tracker, https://github.com/redis/redis-py/issues
Keywords: wivw,wivw store,wivw database
Platform: UNKNOWN
Classifier: Development Status :: 5 - Production/Stable
Classifier: Environment :: Console
Classifier: Intended Audience :: Developers
Classifier: License :: OSI Approved :: MIT License
Classifier: Operating System :: OS Independent
Classifier: Programming Language :: Python
Classifier: Programming Language :: Python :: 3
Classifier: Programming Language :: Python :: 3 :: Only
Classifier: Programming Language :: Python :: 3.6
Classifier: Programming Language :: Python :: 3.7
Classifier: Programming Language :: Python :: 3.8
Classifier: Programming Language :: Python :: 3.9
Classifier: Programming Language :: Python :: 3.10
Classifier: Programming Language :: Python :: 3.11
Classifier: Programming Language :: Python :: Implementation :: CPython
Classifier: Programming Language :: Python :: Implementation :: PyPy
Requires-Python: >=3.6
Requires-Dist: packaging (>=20.4)
Requires-Dist: importlib-metadata (>=1.0) ; python_version < "3.8"
Provides-Extra: hiredis
Requires-Dist: hiredis (>=1.0.0) ; extra == 'hiredis'
Provides-Extra: ocsp
Requires-Dist: cryptography (>=36.0.1) ; extra == 'ocsp'
Requires-Dist: pyopenssl (==20.0.1) ; extra == 'ocsp'
Requires-Dist: requests (>=2.26.0) ; extra == 'ocsp'
